{
    "slider":[
       {
          "img":"https://en.wikipedia.org/wiki/Doha#/media/File:Doha_West_Bay_Skyline_Qatar_Jan_2020.jpg",
          "type":"none",
          "link":"null"
       },
       {
          "img":"https://en.wikipedia.org/wiki/Doha#/media/File:Doha_West_Bay_Skyline_Qatar_Jan_2020.jpg",
          "type":"external",
          "link":"https://aqarco.qa/"
       },
       {
          "img":"https://en.wikipedia.org/wiki/Doha#/media/File:Doha_West_Bay_Skyline_Qatar_Jan_2020.jpg",
          "type":"internal",
          "link":"23"
       }
    ],
    "categories":[
       {
          "namear":"فلل",
          "nameen":"Villas",
          "namefr":"Villas",
          "nametu":"villalar",
          "img":"https://assets-news.housing.com/news/wp-content/uploads/2022/02/27121904/featured-compressed-67.jpg"
       },
       {
          "namear":"شقق",
          "nameen":"Apartments",
          "namefr":"Appartements",
          "nametu":"Daireler",
          "img":"https://samujana.com/wp-content/uploads/2022/04/slider_samujana_villa_01b.jpeg"
       }
    ]
 }